brainprep/__init__.py
brainprep/color_utils.py
brainprep/connectivity.py
brainprep/cortical.py
brainprep/deface.py
brainprep/info.py
brainprep/plotting.py
brainprep/qc.py
brainprep/spatial.py
brainprep/tbss.py
brainprep/utils.py
brainprep/resources/MNI152_T1_1mm_brain.nii.gz
brainprep/resources/cat12vbm_matlabbatch.m
brainprep/resources/cat12vbm_matlabbatch_longitudinal.m
brainprep/scripts/brainprep
brainprep/tests/test_preprocessing.py
brainprep/workflow/__init__.py
brainprep/workflow/cat12vbm.py
brainprep/workflow/deface.py
brainprep/workflow/fmriprep.py
brainprep/workflow/fsreconall.py
brainprep/workflow/mriqc.py
brainprep/workflow/prequal.py
brainprep/workflow/quasiraw.py
brainprep/workflow/tbss.py
brainprep/workflow/resources/iqm_T1w.csv
brainprep/workflow/resources/iqm_T2w.csv
brainprep/workflow/resources/iqm_bold.csv
brainprep/workflow/resources/iqm_desc.csv
brainprep/workflow/resources/iqm_select.tsv
brainprep-0.0.2.data/scripts/brainprep
brainprep-0.0.2.dist-info/licenses/AUTHORS.rst
brainprep-0.0.2.dist-info/licenses/LICENSE.rst
brainprep-0.0.2.dist-info/METADATA
brainprep-0.0.2.dist-info/WHEEL
brainprep-0.0.2.dist-info/top_level.txt
brainprep-0.0.2.dist-info/RECORD
