Metadata-Version: 2.4
Name: brainprep
Version: 0.0.2
Author-email: brainprep developers <antoine.grigis@cea.fr>
License-Expression: CECILL-B
Project-URL: Source, https://github.com/neurospin-deepinsight/brainprep
Project-URL: Tracker, https://github.com/neurospin-deepinsight/brainprep/issues
Platform: Linux
Platform: OSX
Classifier: Development Status :: 1 - Planning
Classifier: Environment :: Console
Classifier: Operating System :: OS Independent
Classifier: Programming Language :: Python
Classifier: Topic :: Scientific/Engineering
Requires-Python: >=3.9
License-File: LICENSE.rst
License-File: AUTHORS.rst
Requires-Dist: numpy
Requires-Dist: nibabel
Requires-Dist: pandas
Requires-Dist: scikit-learn
Requires-Dist: nilearn
Requires-Dist: matplotlib
Requires-Dist: seaborn
Requires-Dist: requests
Requires-Dist: progressbar2
Requires-Dist: fire
Dynamic: license-file
